{
  "color": {
    "primary": {
      "value": "#0b67ff",
      "type": "color",
      "comment": "primary brand color"
    },
    "primary-600": {
      "value": "#0a56e6",
      "type": "color"
    },
    "bg": {
      "value": "{color.primary}",
      "type": "color"
    },
    "text": {
      "value": "#0f1724",
      "type": "color"
    },
    "text-muted": {
      "value": "#64748b",
      "type": "color"
    }
  },
  "spacing": {
    "1": { "value": "4px", "type": "spacing" },
    "2": { "value": "8px", "type": "spacing" },
    "3": { "value": "12px", "type": "spacing" },
    "4": { "value": "16px", "type": "spacing" }
  },
  "radius": {
    "sm": { "value": "4px", "type": "borderRadius" },
    "md": { "value": "8px", "type": "borderRadius" },
    "full": { "value": "9999px", "type": "borderRadius" }
  },
  "typography": {
    "body": {
      "fontSize": { "value": "16px", "type": "fontSize" },
      "lineHeight": { "value": "24px", "type": "lineHeight" }
    },
    "heading": {
      "fontSize": { "value": "24px", "type": "fontSize" },
      "lineHeight": { "value": "32px", "type": "lineHeight" },
      "fontWeight": { "value": "600", "type": "fontWeight" }
    }
  }
}
